LICENCE.txt
README.rst
__buildnumber__.py
__version__.py
setup.py
versao.py
colibri_packaging/7za.exe
colibri_packaging/__init__.py
colibri_packaging/__main__.py
colibri_packaging/empacotar.py
colibri_packaging.egg-info/PKG-INFO
colibri_packaging.egg-info/SOURCES.txt
colibri_packaging.egg-info/dependency_links.txt
colibri_packaging.egg-info/top_level.txt
tests/test_obter_arquivos.py