Metadata-Version: 2.1
Name: colibri-packaging
Version: 2.2.0.1
Summary: Colibri Master Packages generator
Author: Colibri Agile
Author-email: colibri.agile@gmail.com
Platform: Windows
Classifier: Programming Language :: Python :: 3.11
Requires-Python: >=3.11
License-File: LICENCE.txt
